scripts/build_and_publish.py
scripts/build_obfuscated.py
scripts/deploy_simple.py
scripts/deploy_to_pypi.py
scripts/setup_dev_env.py
whatsapp_evie/__init__.py
whatsapp_evie/cli.py
whatsapp_evie/client.py
whatsapp_evie/config.py
whatsapp_evie/exceptions.py
whatsapp_evie/logging_utils.py
whatsapp_evie/models.py
whatsapp_evie/utils.py
whatsapp_evie-1.0.0.dist-info/licenses/LICENSE
whatsapp_evie-1.0.0.dist-info/METADATA
whatsapp_evie-1.0.0.dist-info/WHEEL
whatsapp_evie-1.0.0.dist-info/entry_points.txt
whatsapp_evie-1.0.0.dist-info/top_level.txt
whatsapp_evie-1.0.0.dist-info/RECORD
