Metadata-Version: 2.4
Name: whatsapp-evie
Version: 1.0.0
Summary: A professional Python library for WhatsApp-Evie integration with comprehensive messaging capabilities
Home-page: https://evolvis.ai
Author: Alban Maxhuni, PhD
Author-email: Evolvis AI <a.maxhuni@evolvis.ai>
Maintainer-email: Evolvis AI <contact@evolvis.ai>
License: MIT License
Project-URL: Homepage, https://github.com/evolvis-ai/whatsapp-evie
Project-URL: Documentation, https://whatsapp-evie.readthedocs.io/
Project-URL: Repository, https://github.com/evolvis-ai/whatsapp-evie
Project-URL: Bug Reports, https://github.com/evolvis-ai/whatsapp-evie/issues
Project-URL: Changelog, https://github.com/evolvis-ai/whatsapp-evie/blob/main/CHANGELOG.md
Keywords: whatsapp,messaging,api,webhook,integration,evie,chat,communication
Classifier: Development Status :: 4 - Beta
Classifier: Intended Audience :: Developers
Classifier: License :: OSI Approved :: MIT License
Classifier: Operating System :: OS Independent
Classifier: Programming Language :: Python :: 3
Classifier: Programming Language :: Python :: 3.8
Classifier: Programming Language :: Python :: 3.9
Classifier: Programming Language :: Python :: 3.10
Classifier: Programming Language :: Python :: 3.11
Classifier: Programming Language :: Python :: 3.12
Classifier: Topic :: Communications :: Chat
Classifier: Topic :: Software Development :: Libraries :: Python Modules
Classifier: Topic :: Internet :: WWW/HTTP :: Dynamic Content
Classifier: Typing :: Typed
Requires-Python: >=3.8
License-File: LICENSE
Requires-Dist: aiohttp>=3.9.0
Requires-Dist: pydantic>=2.5.0
Requires-Dist: python-dotenv>=1.0.0
Requires-Dist: requests>=2.31.0
Provides-Extra: dev
Requires-Dist: pytest<9.0.0,>=8.0.0; extra == "dev"
Requires-Dist: pytest-asyncio<1.0.0,>=0.23.0; extra == "dev"
Requires-Dist: pytest-cov<6.0.0,>=4.0.0; extra == "dev"
Requires-Dist: black>=23.0.0; extra == "dev"
Requires-Dist: isort>=5.12.0; extra == "dev"
Requires-Dist: flake8>=6.0.0; extra == "dev"
Requires-Dist: mypy>=1.0.0; extra == "dev"
Requires-Dist: pre-commit>=3.0.0; extra == "dev"
Requires-Dist: twine>=4.0.0; extra == "dev"
Requires-Dist: build>=0.10.0; extra == "dev"
Provides-Extra: test
Requires-Dist: pytest<9.0.0,>=8.0.0; extra == "test"
Requires-Dist: pytest-asyncio<1.0.0,>=0.23.0; extra == "test"
Requires-Dist: pytest-cov<6.0.0,>=4.0.0; extra == "test"
Provides-Extra: docs
Requires-Dist: sphinx>=5.0.0; extra == "docs"
Requires-Dist: sphinx-rtd-theme>=1.2.0; extra == "docs"
Requires-Dist: myst-parser>=0.18.0; extra == "docs"
Provides-Extra: obfuscation
Requires-Dist: pyarmor>=8.0.0; extra == "obfuscation"
Dynamic: author
Dynamic: home-page
Dynamic: license-file
Dynamic: requires-python
